django_sso_app/__init__.py
django_sso_app/admin.py
django_sso_app/app_settings.py
django_sso_app/apps.py
django_sso_app/manage.py
django_sso_app/models.py
django_sso_app/settings.py
django_sso_app/urls.py
django_sso_app/app/__init__.py
django_sso_app/app/settings.py
django_sso_app/app/urls.py
django_sso_app/app/views.py
django_sso_app/backend/__init__.py
django_sso_app/backend/settings.py
django_sso_app/backend/urls.py
django_sso_app/core/__init__.py
django_sso_app/core/adapter.py
django_sso_app/core/app_settings.py
django_sso_app/core/context_processors.py
django_sso_app/core/exceptions.py
django_sso_app/core/forms.py
django_sso_app/core/functions.py
django_sso_app/core/loader.py
django_sso_app/core/mixins.py
django_sso_app/core/models.py
django_sso_app/core/permissions.py
django_sso_app/core/serializers.py
django_sso_app/core/to_translate.py
django_sso_app/core/urls.py
django_sso_app/core/utils.py
django_sso_app/core/views.py
django_sso_app/core/api/__init__.py
django_sso_app/core/api/authentication.py
django_sso_app/core/api/serializers.py
django_sso_app/core/api/urls.py
django_sso_app/core/api/utils.py
django_sso_app/core/api/views.py
django_sso_app/core/api/tests/__init__.py
django_sso_app/core/api/tests/test_views.py
django_sso_app/core/apps/__init__.py
django_sso_app/core/apps/tests.py
django_sso_app/core/apps/api_gateway/__init__.py
django_sso_app/core/apps/api_gateway/functions.py
django_sso_app/core/apps/api_gateway/utils.py
django_sso_app/core/apps/api_gateway/kong/__init__.py
django_sso_app/core/apps/api_gateway/kong/functions.py
django_sso_app/core/apps/api_gateway/kong/utils.py
django_sso_app/core/apps/api_gateway/signals/__init__.py
django_sso_app/core/apps/api_gateway/signals/app.py
django_sso_app/core/apps/api_gateway/signals/backend.py
django_sso_app/core/apps/api_gateway/tests/__init__.py
django_sso_app/core/apps/api_gateway/tests/test_views.py
django_sso_app/core/apps/devices/__init__.py
django_sso_app/core/apps/devices/admin.py
django_sso_app-0.12.0.dist-info/AUTHORS.rst
django_sso_app-0.12.0.dist-info/LICENSE
django_sso_app-0.12.0.dist-info/METADATA
django_sso_app-0.12.0.dist-info/SOURCES.txt.py
django_sso_app-0.12.0.dist-info/WHEEL
django_sso_app-0.12.0.dist-info/dependency_links.txt.py
django_sso_app-0.12.0.dist-info/requires.txt.py
django_sso_app-0.12.0.dist-info/top_level.txt
django_sso_app-0.12.0.dist-info/top_level.txt.py
django_sso_app-0.12.0.dist-info/RECORD
